{"data": [{"author_id": "136361303", "public_metrics": {"retweet_count": 21755, "reply_count": 1385, "like_count": 117457, "quote_count": 3825}, "id": "1327240359898992646", "text": ".@harry_styles is our December issue cover star!\n\nRead how the star is making and playing by his own rules: https://t.co/tQPLi5OEtj https://t.co/AxZgxE68Rx", "sentiment_score": 0.9734679460525513}, {"author_id": "136361303", "public_metrics": {"retweet_count": 3, "reply_count": 4, "like_count": 81, "quote_count": 0}, "id": "1334769627306536961", "text": "Gillian Anderson takes on the role of a lifetime as British prime minister Margaret Thatcher in season 4 of #TheCrown. https://t.co/bf6fG7FrFe", "sentiment_score": 0.9477847814559937}, {"author_id": "136361303", "public_metrics": {"retweet_count": 19, "reply_count": 2, "like_count": 200, "quote_count": 1}, "id": "1334763848168075264", "text": ".@HaileeSteinfeld shares all of her #beautysecrets with us https://t.co/hH8nE7wSXt", "sentiment_score": 0.7650316953659058}, {"author_id": "136361303", "public_metrics": {"retweet_count": 2, "reply_count": 3, "like_count": 86, "quote_count": 0}, "id": "1334758147374927878", "text": "The bright, color-blocked tops have become the waist-up Zoom style during COVID-19. https://t.co/Y8uMctHEvG", "sentiment_score": 0.8497348427772522}, {"author_id": "136361303", "public_metrics": {"retweet_count": 15, "reply_count": 4, "like_count": 361, "quote_count": 2}, "id": "1334752325970300928", "text": "We meet @RachelZegler on the brink of her biggest year yet. https://t.co/cZIGAEW2VO", "sentiment_score": 0.21184459328651428}, {"author_id": "136361303", "public_metrics": {"retweet_count": 3, "reply_count": 3, "like_count": 64, "quote_count": 0}, "id": "1334746990157115392", "text": "Look no further than these must-have styles even Vogue editors don\u2019t want to take off.  https://t.co/KrOU8l3N3q", "sentiment_score": 0.5}, {"author_id": "136361303", "public_metrics": {"retweet_count": 19, "reply_count": 3, "like_count": 147, "quote_count": 2}, "id": "1334741141623861251", "text": "An expert explains a DIY lymphatic drainage approach you can do at home, step by step. https://t.co/W7YboI66cg", "sentiment_score": 0.5}, {"author_id": "136361303", "public_metrics": {"retweet_count": 5, "reply_count": 2, "like_count": 74, "quote_count": 0}, "id": "1334735214963281920", "text": "The 23-year-old breakout star of Industry\u2014an HBO series about entry-level investment bankers in London\u2013takes us through the steps to refining the art of the Zoom audition, which proved most valuable to her career this year. https://t.co/SJl6QDM6yL", "sentiment_score": 0.9553933143615723}, {"author_id": "136361303", "public_metrics": {"retweet_count": 40, "reply_count": 7, "like_count": 589, "quote_count": 5}, "id": "1334729241271918595", "text": "45 incredible #MetGala looks from the '90s https://t.co/vwQ3nnuAhI https://t.co/bOPRPnlnZI", "sentiment_score": 0.9384987950325012}, {"author_id": "136361303", "public_metrics": {"retweet_count": 1, "reply_count": 1, "like_count": 67, "quote_count": 0}, "id": "1334723592584654848", "text": "Wellness brands are tapping collagen\u2019s inside-out benefits, from plumper skin to a stronger immune system. Here are some of our favorites so far. https://t.co/67oRLAiQwF", "sentiment_score": 0.9144160747528076}, {"author_id": "136361303", "public_metrics": {"retweet_count": 9, "reply_count": 2, "like_count": 79, "quote_count": 2}, "id": "1334717275329482754", "text": ".@JLO's new skin-care line, JLo Beauty, essentially packages what Lopez refers to as \u201cthe 5 Ss:\u201d sleep, sunscreen, serum, supplements and sano, a riff on the Spanish phrase vivir sano, to live healthily. https://t.co/CbpA1OLbOe", "sentiment_score": 0.5}, {"author_id": "136361303", "public_metrics": {"retweet_count": 3, "reply_count": 1, "like_count": 93, "quote_count": 0}, "id": "1334711995019440130", "text": "Irina Shayk is a master of outr\u00e9 combos https://t.co/i5b9v3kf78", "sentiment_score": 0.5}, {"author_id": "136361303", "public_metrics": {"retweet_count": 5, "reply_count": 5, "like_count": 146, "quote_count": 1}, "id": "1334703873165053962", "text": ".@DuaLipa's latest ensemble is fresh from the runway. https://t.co/Iy0jq3MPhA", "sentiment_score": 0.8471055030822754}, {"author_id": "136361303", "public_metrics": {"retweet_count": 7, "reply_count": 1, "like_count": 51, "quote_count": 1}, "id": "1334696849811402752", "text": "Take the stress out of holiday shopping with our list of 36 of the best gifts for every man in your life. https://t.co/WJBDlbmIWB", "sentiment_score": 0.9839969277381897}, {"author_id": "136361303", "public_metrics": {"retweet_count": 6, "reply_count": 0, "like_count": 85, "quote_count": 1}, "id": "1334690261469958147", "text": "Give your skin the nourishing boost it deserves. https://t.co/1rfoHAx1mr", "sentiment_score": 0.9737436175346375}, {"author_id": "136361303", "public_metrics": {"retweet_count": 5, "reply_count": 1, "like_count": 47, "quote_count": 1}, "id": "1334684338550677504", "text": "Saskia de Rothschild uses her training as a journalist to tell the story of her family\u2019s estate. https://t.co/WSPrZdnwnG", "sentiment_score": 0.5}, {"author_id": "136361303", "public_metrics": {"retweet_count": 10, "reply_count": 3, "like_count": 124, "quote_count": 0}, "id": "1334676556753625089", "text": ".@SharonStone looks back at the opulent costuming of Ginger in Martin Scorsese\u2019s Las Vegas masterpiece on its 25th anniversary. https://t.co/N8OtTErahx", "sentiment_score": 0.9794710874557495}, {"author_id": "136361303", "public_metrics": {"retweet_count": 11, "reply_count": 0, "like_count": 174, "quote_count": 7}, "id": "1334671014693920771", "text": "An exhaustive list of the best romantic comedies for any and all occasions. https://t.co/2Etmq4Hqq8", "sentiment_score": 0.9930768013000488}, {"author_id": "136361303", "public_metrics": {"retweet_count": 7, "reply_count": 4, "like_count": 81, "quote_count": 4}, "id": "1334665031359852546", "text": "Eight years ago, Italian paralympian Veronica Yoko Plebani found a new beginning. At 15, Plebani, now 23, contracted an acute case of bacterial meningitis that left her body, particularly her arms and legs, severely scarred and impaired. #vogueworld https://t.co/Vn2F06MY9X", "sentiment_score": 0.08845135569572449}, {"author_id": "136361303", "public_metrics": {"retweet_count": 3, "reply_count": 0, "like_count": 54, "quote_count": 0}, "id": "1334657327811731457", "text": "Chef Kia Damon is reforming toxic kitchen culture in more ways than one. https://t.co/QCCRkxyBpW", "sentiment_score": 0.22347697615623474}, {"author_id": "136361303", "public_metrics": {"retweet_count": 6, "reply_count": 2, "like_count": 54, "quote_count": 1}, "id": "1334651233932603396", "text": "Aurora James, Bethany Williams, Grace Wales Bonner, Stella McCartney, and Kim Jones are among the talents shaping a kinder, fairer fashion industry. From fighting racism to tackling climate change, this\u2014in the winners\u2019 own words\u2014is why fashion matters now https://t.co/KgUHdtfLtO", "sentiment_score": 0.9995644092559814}, {"author_id": "136361303", "public_metrics": {"retweet_count": 6, "reply_count": 6, "like_count": 160, "quote_count": 1}, "id": "1334643197235093506", "text": "TikTok Star @JasmineChiswell lives in Marilyn Monroe\u2019s house in 2020, has perfectly coiffed platinum blonde hair, a penchant for red lipstick, and a wardrobe of exclusively 1950s dresses. https://t.co/aniNMALXdx", "sentiment_score": 0.9952811002731323}, {"author_id": "136361303", "public_metrics": {"retweet_count": 7, "reply_count": 2, "like_count": 99, "quote_count": 0}, "id": "1334635559290101762", "text": "The number one culprit? Not washing your hair. https://t.co/iKpFZbs7PH", "sentiment_score": 0.8232924938201904}, {"author_id": "136361303", "public_metrics": {"retweet_count": 5, "reply_count": 2, "like_count": 117, "quote_count": 3}, "id": "1334625066039074822", "text": "She's on to something. https://t.co/5mayvNNw8L", "sentiment_score": 0.832504391670227}, {"author_id": "136361303", "public_metrics": {"retweet_count": 6, "reply_count": 3, "like_count": 58, "quote_count": 0}, "id": "1334619299894472708", "text": "A new player on the Indigenous streetwear scene is Primer Rebelde De America, a one-year-old brand founded by Victor Vegas and Liana Waller. https://t.co/AAHnz8CdTo", "sentiment_score": 0.5}, {"author_id": "136361303", "public_metrics": {"retweet_count": 24, "reply_count": 2, "like_count": 186, "quote_count": 2}, "id": "1334610948657655812", "text": ".@ZaraLarsson guides us through a week\u2019s worth of city life, from performing at the #MTVEMAs to chilling in her garden, in her photo diary for Vogue. https://t.co/ID4h3HQu51 https://t.co/gRaE0LGQrx", "sentiment_score": 0.9624955654144287}, {"author_id": "136361303", "public_metrics": {"retweet_count": 131, "reply_count": 35, "like_count": 885, "quote_count": 32}, "id": "1334604857353920516", "text": "In honor of @ShawnMendes\u2019s new album, his longtime stylist Tiffany Briseno spoke with Vogue exclusively to give us a behind-the-scenes look at some of the singer\u2019s recent performance looks. https://t.co/Eu7TYgBzGl", "sentiment_score": 0.9771995544433594}, {"author_id": "136361303", "public_metrics": {"retweet_count": 3, "reply_count": 4, "like_count": 75, "quote_count": 2}, "id": "1334596464635416576", "text": "\u201cI felt that I was doing something for female empowerment by ridding [the space of] bad karma and the things that went on in that organization,\u201d @msbarbarak says. https://t.co/UWRjAnE3uP", "sentiment_score": 0.1214260458946228}, {"author_id": "136361303", "public_metrics": {"retweet_count": 7, "reply_count": 0, "like_count": 72, "quote_count": 1}, "id": "1334588136198975491", "text": "\u201cWe have always existed and will continue to exist,\" Brazilian model and trans activist Valentina Sampaio says. \"It is important to honor the community all year round.\u201d https://t.co/npx6hsB36M", "sentiment_score": 0.8779382705688477}, {"author_id": "136361303", "public_metrics": {"retweet_count": 17, "reply_count": 4, "like_count": 177, "quote_count": 2}, "id": "1334580156543938561", "text": "Kate Middleton wore a Gabriela Hearst denim dress with a sustainable twist to meet with Sir David Attenborough. https://t.co/ODQIsSK4tp", "sentiment_score": 0.5}, {"author_id": "136361303", "public_metrics": {"retweet_count": 5, "reply_count": 0, "like_count": 135, "quote_count": 3}, "id": "1334572589562417155", "text": "If a star of @MileyCyrus's stature is willing to speak out about the difficulty of remaining sober in a time of global emergency, maybe the stigma can be somewhat lessened. https://t.co/f3YasR3fbb", "sentiment_score": 0.05469226837158203}, {"author_id": "136361303", "public_metrics": {"retweet_count": 4, "reply_count": 1, "like_count": 55, "quote_count": 0}, "id": "1334567184006307841", "text": "Over the course of her career as an author and activist, @IjeomaOluo has been conscious to balance output with self-care, saying: \u201cMy work is very difficult emotionally, and it takes me a lot of time, a lot of effort. I'm spending a lot of time in trauma.\" https://t.co/9LSYQ2AdpB", "sentiment_score": 0.004407823085784912}, {"author_id": "21401466", "public_metrics": {"retweet_count": 35, "reply_count": 1, "like_count": 215, "quote_count": 9}, "id": "1334555325765218312", "text": ".@rosalia, @priyankachopra, and @Maisie_Williams will be hosting the British Fashion Council\u2019s (@BFC) #FashionAwards tonight\u2014but the ceremony will be unlike any other in the recent past. Here's how to watch: https://t.co/DF6Uc5qI3t https://t.co/1BtxFtyTdU", "sentiment_score": 0.5}, {"author_id": "136361303", "public_metrics": {"retweet_count": 7, "reply_count": 1, "like_count": 58, "quote_count": 0}, "id": "1334559054342090755", "text": "Tune in for the first-of-its kind ceremony today, streaming exclusively on the @BFC Fashion Awards website. https://t.co/KQcAK3ckDf", "sentiment_score": 0.5}, {"author_id": "136361303", "public_metrics": {"retweet_count": 2, "reply_count": 2, "like_count": 82, "quote_count": 1}, "id": "1334553935219216385", "text": "How well do you know #TheUndoing star? https://t.co/wnsBA7VO40", "sentiment_score": 0.9886132478713989}], "user_info": {"name": "Vogue Magazine", "username": "voguemagazine", "id": "136361303", "public_metrics": {"followers_count": 13800366, "following_count": 462, "tweet_count": 161104, "listed_count": 21831}}}